autopub/__init__.py
autopub/autopub.py
autopub/base.py
autopub/build_release.py
autopub/check_release.py
autopub/commit_release.py
autopub/create_github_release.py
autopub/deploy_release.py
autopub/github_contributor.py
autopub/prepare_release.py
autopub/publish_release.py
autopub/vendor/__init__.py
autopub/vendor/github_release.py
autopub-0.4.1.dist-info/LICENSE
autopub-0.4.1.dist-info/METADATA
autopub-0.4.1.dist-info/WHEEL
autopub-0.4.1.dist-info/entry_points.txt
autopub-0.4.1.dist-info/RECORD
