Metadata-Version: 2.1
Name: autopub
Version: 0.4.1
Summary: Automatic package release upon pull request merge
Home-page: https://github.com/autopub/autopub
License: AGPL-3.0
Keywords: automatic,packaging,publish,release,version
Author: Justin Mayer
Author-email: entroP@gmail.com
Requires-Python: >=3.10.0,<4.0
Classifier: Development Status :: 4 - Beta
Classifier: Environment :: Console
Classifier: Intended Audience :: Developers
Classifier: License :: OSI Approved :: GNU Affero General Public License v3
Classifier: Operating System :: OS Independent
Classifier: Programming Language :: Python :: 3
Classifier: Programming Language :: Python :: 3.10
Classifier: Programming Language :: Python :: 3.11
Classifier: Programming Language :: Python :: 3.12
Classifier: Programming Language :: Python :: 3.13
Classifier: Topic :: Software Development :: Libraries :: Python Modules
Classifier: Topic :: System :: Software Distribution
Classifier: Topic :: System :: Systems Administration
Provides-Extra: github
Requires-Dist: backoff (>=2.1.2,<2.2.0) ; extra == "github"
Requires-Dist: build (>=0.10.0)
Requires-Dist: click ; extra == "github"
Requires-Dist: dunamai (>=1.17.0)
Requires-Dist: httpx ; extra == "github"
Requires-Dist: linkheader ; extra == "github"
Requires-Dist: requests ; extra == "github"
Requires-Dist: tomlkit (>=0.5)
Requires-Dist: twine (>=4.0.2)
Project-URL: Issue Tracker, https://github.com/autopub/autopub/issues
Project-URL: Repository, https://github.com/autopub/autopub
